hashtag_utils/__init__.py
hashtag_utils/common.py
hashtag_utils/hashtag_utils.py
hashtag_utils-0.5.6.dist-info/LICENSE
hashtag_utils-0.5.6.dist-info/METADATA
hashtag_utils-0.5.6.dist-info/WHEEL
hashtag_utils-0.5.6.dist-info/top_level.txt
hashtag_utils-0.5.6.dist-info/RECORD
