Metadata-Version: 2.1
Name: hashtag_utils
Version: 0.5.6
Summary: Simple LLM-powered hashtag utilities.
Home-page: http://github.com/AdiPat/hashtag_utils
Author: Aditya Patange
Author-email: contact.adityapatange@gmail.com
Classifier: License :: OSI Approved :: MIT License
Classifier: Programming Language :: Python
Classifier: Programming Language :: Python :: 3
Classifier: Programming Language :: Python :: 3.9
License-File: LICENSE
Requires-Dist: openai
Requires-Dist: python-dotenv
